MaterialX/__init__.py
MaterialX/_scripts/__init__.py
MaterialX/_scripts/baketextures.py
MaterialX/_scripts/creatematerial.py
MaterialX/_scripts/generateshader.py
MaterialX/_scripts/genmdl.py
MaterialX/_scripts/mxdoc.py
MaterialX/_scripts/mxformat.py
MaterialX/_scripts/mxvalidate.py
MaterialX/_scripts/README.md
MaterialX/_scripts/translateshader.py
MaterialX/_scripts/writenodegraphs.py
MaterialX/datatype.py
MaterialX/libraries/bxdf/disney_principled.mtlx
MaterialX/libraries/bxdf/genglsl/gltf_pbr.mtlx
MaterialX/libraries/bxdf/genglsl/open_pbr_surface.mtlx
MaterialX/libraries/bxdf/genglsl/standard_surface.mtlx
MaterialX/libraries/bxdf/genmdl/open_pbr_surface.mtlx
MaterialX/libraries/bxdf/gltf_pbr.mtlx
MaterialX/libraries/bxdf/lama/lama_add.mtlx
MaterialX/libraries/bxdf/lama/lama_conductor.mtlx
MaterialX/libraries/bxdf/lama/lama_dielectric.mtlx
MaterialX/libraries/bxdf/lama/lama_diffuse.mtlx
MaterialX/libraries/bxdf/lama/lama_emission.mtlx
MaterialX/libraries/bxdf/lama/lama_generalized_schlick.mtlx
MaterialX/libraries/bxdf/lama/lama_iridescence.mtlx
MaterialX/libraries/bxdf/lama/lama_layer.mtlx
MaterialX/libraries/bxdf/lama/lama_mix.mtlx
MaterialX/libraries/bxdf/lama/lama_sheen.mtlx
MaterialX/libraries/bxdf/lama/lama_sss.mtlx
MaterialX/libraries/bxdf/lama/lama_surface.mtlx
MaterialX/libraries/bxdf/lama/lama_translucent.mtlx
MaterialX/libraries/bxdf/open_pbr_surface.mtlx
MaterialX/libraries/bxdf/standard_surface.mtlx
MaterialX/libraries/bxdf/translation/open_pbr_to_standard_surface.mtlx
MaterialX/libraries/bxdf/translation/standard_surface_to_gltf_pbr.mtlx
MaterialX/libraries/bxdf/translation/standard_surface_to_open_pbr.mtlx
MaterialX/libraries/bxdf/translation/standard_surface_to_usd.mtlx
MaterialX/libraries/bxdf/usd_preview_surface.mtlx
MaterialX/libraries/cmlib/cmlib_defs.mtlx
MaterialX/libraries/cmlib/cmlib_ng.mtlx
MaterialX/libraries/lights/genglsl/lights_genglsl_impl.mtlx
MaterialX/libraries/lights/genglsl/mx_directional_light.glsl
materialx-1.39.4.dist-info/METADATA
materialx-1.39.4.dist-info/WHEEL
materialx-1.39.4.dist-info/entry_points.txt
materialx-1.39.4.dist-info/licenses/LICENSE
materialx-1.39.4.dist-info/RECORD
