Metadata-Version: 2.1
Name: MaterialX
Version: 1.39.4
Author-Email: Contributors to the MaterialX project <materialx-discussion@lists.aswf.io>
Classifier: Programming Language :: Python :: 3
Classifier: License :: OSI Approved :: Apache Software License
Classifier: Operating System :: OS Independent
Project-URL: Homepage, https://materialx.org
Project-URL: Source, https://github.com/AcademySoftwareFoundation/MaterialX
Project-URL: Bug Tracker, https://github.com/AcademySoftwareFoundation/MaterialX/issues
Requires-Python: >=3.9
